positional_encodings/__init__.py
positional_encodings/tf_encodings.py
positional_encodings/torch_encodings.py
positional_encodings-6.0.4.dist-info/LICENSE
positional_encodings-6.0.4.dist-info/METADATA
positional_encodings-6.0.4.dist-info/WHEEL
positional_encodings-6.0.4.dist-info/top_level.txt
positional_encodings-6.0.4.dist-info/RECORD
