Metadata-Version: 2.1
Name: positional-encodings
Version: 6.0.4
Summary: 1D, 2D, and 3D Sinusodal Positional Encodings in PyTorch
Home-page: https://github.com/tatp22/multidim-positional-encoding
Author: Peter Tatkowski
Author-email: tatp22@gmail.com
Keywords: transformers,attention
Classifier: Programming Language :: Python :: 3
Classifier: License :: OSI Approved :: MIT License
Classifier: Operating System :: OS Independent
Requires-Python: >=3.12
License-File: LICENSE
Requires-Dist: numpy
Provides-Extra: pytorch
Requires-Dist: torch; extra == "pytorch"
Provides-Extra: tensorflow
Requires-Dist: tensorflow; extra == "tensorflow"
